visor_image/__init__.py
visor_image/images.py
visor_image/io.py
visor_image_suite-2024.10.0.dist-info/LICENSE
visor_image_suite-2024.10.0.dist-info/METADATA
visor_image_suite-2024.10.0.dist-info/WHEEL
visor_image_suite-2024.10.0.dist-info/top_level.txt
visor_image_suite-2024.10.0.dist-info/RECORD
